pycsio/SM3.py
pycsio/SM4.py
pycsio/__init__.py
pycsio/baseConverter.py
pycsio/baseConverterDecimal.py
pycsio/crypto.py
pycsio/directory.py
pycsio/file.py
pycsio/hasher.py
pycsio/hexBytesConverter.py
pycsio/logger.py
pycsio/padding.py
pycsio/path.py
pycsio/string.py
pycsio-0.1.7.dist-info/METADATA
pycsio-0.1.7.dist-info/WHEEL
pycsio-0.1.7.dist-info/top_level.txt
pycsio-0.1.7.dist-info/RECORD
