Metadata-Version: 2.4
Name: pycsio
Version: 0.1.7
Summary: My useful Tools
Home-page: https://github.com/admin
Author: admin
Author-email: admin@email.com
Requires-Dist: tqdm
Requires-Dist: numba
Requires-Dist: numpy
Requires-Dist: rich
Requires-Dist: imagehash
Requires-Dist: pillow
Requires-Dist: pycryptodome
Dynamic: author
Dynamic: author-email
Dynamic: home-page
Dynamic: requires-dist
Dynamic: summary
